inc/project_defines.v
/*
    This file have macros for address, intial values, number of registers and register width.
    Parameters are updated from this definition. DO NOT change it in other files or in instantiation (only do that for testing).

    REGS/REGISTERS/.. refers to normal registers.
    REQUEST_REGS/TRIGGER_REGS/... refers to registers that are erased after acknowledge the data reading.
    REGS_TOTAL/.. reefers to both.
*/

`ifndef __PROJECT_DEFINES_V
`define __PROJECT_DEFINES_V

/*******************************************************************************
                            HARDWARE DEFINITIONS
*******************************************************************************/
`define KILO                1000
`define MEGA                1000*`KILO




/*******************************************************************************
                            HARDWARE DEFINITIONS
*******************************************************************************/
`define CLK_FREQUENCY       128*`MEGA
`define CLOCK_PERIOD_NS     10




/*******************************************************************************
                            MODULATOR DEFINITIONS
*******************************************************************************/

// AM
`define AM_BIT_RESOLUTION       6
`define AM_PWM_STEPS            2**`AM_BIT_RESOLUTION
//`define AM_CARRIER_FREQ     CLK_FREQUENCY/AM_PWM_DIV
`define AM_CARRIER_FREQ         1*`MEGA
`define AM_CLKS_IN_PWM_STEPS    `CLK_FREQUENCY/(`AM_CARRIER_FREQ*`AM_PWM_STEPS)










/////////////////////////////
// USE REAL/FAKE ADCS
// real adc: ADC1175
// default fake adc version: loads rom.hex into a ROM (sinewave) + noise
// alternative fake adc version: counter
// To use fake adcs, add this defines when synthetising:
//  make syn DEF=FAKE_ADC                   # `define FAKE_ADC
//  make syn DEF="FAKE_ADC FAKE_ADC_ALT"    # `define FAKE_ADC_ALT
/////////////////////////////

`define CLK_FREQ        99000000
`define CLOCK_PERIOD_NS 10          // <-- correct this one

`define BAUDRATE        921600

`define __ADC_DF_WIDTH  32
`define __RAM_SIZE_CH   (4096*4)          // RAM for each channel in bits
`define __RAM_SIZE_CH_BYTES = (`__RAM_SIZE_CH / 8)
`define __MA_ACUM_WIDTH 12

/*******************************************************************************
                            HARDWARE DEFINITIONS
*******************************************************************************/
`define __BITS_ADC      8
`define __BITS_DAC      10

/*******************************************************************************
                            BASIC REGISTER DEFINITIONS
*******************************************************************************/

`define __FT245_DATA_WIDTH          8
`define __RX_WIDTH                  8       // Register and address width are a multiple of __RX_WIDTH
`define __TX_WIDTH                  8       //
`define __NUM_REGS                  15
`define __NUM_REQUEST_REGS          1
`define __NUM_REGS_TOTAL            ( __NUM_REGS + `__NUM_REQUEST_REGS )
`define __REG_DATA_WIDTH            16                                          // Register width
`define __REG_ADDR_WIDTH_MIN        ( $clog2( `__NUM_REGS_TOTAL ) )
//__ADDR_WIDTH_MIN rounded to next multiple of a byte
`define __REG_ADDR_WIDTH            ( $rtoi( $ceil( $itor(`__REG_ADDR_WIDTH_MIN) / `__RX_WIDTH ) ) * 8 )
`define __REGS_STARTING_ADDR        1                                           // First reg addr after request regs.

`define __ADC_CLK_DIV_WIDTH         32
`define __MOVING_AVERAGE_ACUM_WIDTH 12

`define __I2C_CLOCK_DIVIDER         1000
`define __I2C_FIFO_LENGTH           16

/*******************************************************************************
                                ADDRESSES
*******************************************************************************/

// Request regs addresses
`define __ADDR_REQUESTS                 0

// Conf regs addresses
`define __ADDR_SETTINGS_CHA             1
`define __ADDR_SETTINGS_CHB             2
`define __ADDR_DAC_I2C                  3
// `define __ADDR_DAC_CHA                  3
// `define __ADDR_DAC_CHB                  4
`define __ADDR_TRIGGER_SETTINGS         5
`define __ADDR_TRIGGER_VALUE            6
`define __ADDR_NUM_SAMPLES              7
`define __ADDR_PRETRIGGER               8
`define __ADDR_ADC_CLK_DIV_CHA_L        9
`define __ADDR_ADC_CLK_DIV_CHA_H        10
`define __ADDR_ADC_CLK_DIV_CHB_L        9
`define __ADDR_ADC_CLK_DIV_CHB_H        10
`define __ADDR_N_MOVING_AVERAGE_CHA     13
`define __ADDR_N_MOVING_AVERAGE_CHB     13

/*******************************************************************************
                                BIT FIELDS
*******************************************************************************/

// SETTINGS_CHA, SETTINGS_CHB
`define __CONF_CH_ATT                       7:5
`define __CONF_CH_GAIN                      4:2
`define __CONF_CH_DC_COUPLING               1:1
`define __CONF_CH_ON                        0:0

// trigger_conf
//`define __TRIGGER_CONF_MODE               3:3
`define __TRIGGER_CONF_SOURCE_SEL           2:1
`define __TRIGGER_CONF_EDGE                 0

// Requests handler
`define __RQST_START_IDX        0
`define __RQST_STOP_IDX         1
`define __RQST_CHA_IDX          2
`define __RQST_CHB_IDX          3
`define __RQST_TRIG_IDX         4
`define __RQST_RST_IDX          5

/*******************************************************************************
                        INITIAL VALUES OF REGESTERS
*******************************************************************************/

`define __DEFAULT_REQUESTS               16'd0
`define __DEFAULT_SETTINGS_CHA           16'b0000000000000011
`define __DEFAULT_SETTINGS_CHB           16'b0000000000000011
// `define __DEFAULT_DAC_CHA                (1 << (`__BITS_DAC-1)) // 16'b1000000000000000
// `define __DEFAULT_DAC_CHB                (1 << (`__BITS_DAC-1)) // 16'b1000000000000000
`define __DEFAULT_DAC_I2C                16'd0
`define __DEFAULT_TRIGGER_SETTINGS       16'd0
`define __DEFAULT_TRIGGER_VALUE          (1 << (`__BITS_ADC-1)) // 16'b10000000
`define __DEFAULT_NUM_SAMPLES            16'd128
`define __DEFAULT_PRETRIGGER             16'd28
`define __DEFAULT_ADC_CLK_DIV_CHA        16'd4
`define __DEFAULT_ADC_CLK_DIV_CHB        16'd4
`define __DEFAULT_N_MOVING_AVERAGE_CHA   16'd0
`define __DEFAULT_N_MOVING_AVERAGE_CHB   16'd0

`endif

modules/counter/module_counter.v
/* counter with programmable module */

module module_counter #(
    parameter WIDTH = 8
)(
    input   clk,
    input   rst,
    input   enable,
    input   [WIDTH-1:0] max_count,
    output  tc
);
    /* Counter register */
    reg [WIDTH-1:0] count;
    reg tc2;
    assign tc=tc2;

    /* always */
    always @ (posedge clk) begin
        tc2 <= 1'b0;

        if (rst == 1'b1)
            count <=0;
        else if ( enable == 1'b1 ) begin
            count <= count + 1;
            if ( count >= max_count ) begin
                count <= 0;
                tc2 <= 1'b1;
            end
        end
    end

endmodule

modules/modulator/modulator.v
`include "../../inc/project_defines.v"

module modulator #(
    parameter FOO = 10,
    parameter AM_CLKS_IN_PWM_STEPS = `AM_CLKS_IN_PWM_STEPS,
    parameter AM_PWM_STEPS = `AM_PWM_STEPS
)(
    input clk,
    input rst,
    input enable,
    /* configuration parameters */
    input [7:0] bits_per_sample,
    input [7:0] clks_per_pwm_step,
    input new_sample,
    /* data flow */
    input [7:0] sample,
    output reg pwm
);
    localparam WIDTH = $clog2(FOO);

    /* registers */
    reg [WIDTH-1:0] count;
    wire tc_pwm_step, tc_pwm_symb;
    reg [AM_PWM_STEPS-1:0] shift_register;
    reg [7:0] sample_reg, counter_duty;
    wire counter_rst;
    assign counter_rst = new_sample | rst;

    // counter to generate ticks at pwm-steps frequency
    module_counter #(
        .WIDTH  (8)
    ) inst_counter_pwm_steps (
        .clk    (clk),
        .rst    (counter_rst),
        .enable (1'b1),
        .max_count (clks_per_pwm_step),
        .tc     (tc_pwm_step)
    );

    // counter to generate ticks at pwm-symbols frequency
    module_counter #(
        .WIDTH  (8)
    ) inst_counter_pwm_symb (
        .clk    (clk),
        .rst    (counter_rst),
        .enable (tc_pwm_step),
        .max_count (bits_per_sample),
        .tc     (tc_pwm_symb)
    );

    // shift register to serialize each pwm-symbol
    always @ (posedge clk) begin
        if (rst == 1'b1) begin
            sample_reg <= 0;
            counter_duty <= 0;
        end else if (enable == 1'b1) begin
            if (new_sample == 1'b1) begin
                counter_duty <= 8'd0;
                sample_reg <= sample;
            end else if (tc_pwm_step == 1'b1) begin
                if(counter_duty > sample_reg)
                    pwm <= 1'b0;
                else begin
                    counter_duty <= counter_duty + 1;
                    pwm <= 1'b1;
                end
            end
        end else begin
            pwm <= 1'b0;
        end
    end

    // // output assignment
    // assign pwm = counter_duty < sample ? 1:0;


endmodule

modules/modulator_am/tb/modulator_tb.v
`include "../../inc/project_defines.v"
`timescale 1 ns/100 ps  // time-unit = 1 ns, precision = 10 ps

module test_modulator;

  reg rst, enable, new_sample;
  wire pwm;
  reg [7:0] sample;
  
  /* Make a regular pulsing clock. */
  reg clk = 0;
  always #10 clk = !clk;


  modulator #(
    .FOO(10),
    .AM_CLKS_IN_PWM_STEPS(10),
    .AM_PWM_STEPS(10)
  ) dut (
    .clk  (clk),
    .rst  (rst),
    .enable (enable),
    /* configuration parameters */
    .bits_per_sample  (8'd255),
    .clks_per_pwm_step(8'd2),
    .new_sample   (new_sample),
    /* data flow */
    .sample       (sample),
    .pwm  (pwm)
  );

  initial begin
      $dumpfile ("waveform.vcd");
      $dumpvars (0,test_modulator);
      rst <= 1;
      enable <= 0;
      new_sample <= 0;
      #20
      rst <= 0;
      #20
      enable <= 1;
      #20
      new_sample <= 1;
      sample <= 8'd128;
      #20
      new_sample <= 0;
      #50120;
      new_sample <= 1;
      sample <= 8'd10;
      #20
      new_sample <= 0;
      #10240;
      $finish;

  end

endmodule

modules/modulator/waveform.vcd
$date
	Sun Sep 29 22:43:52 2019
$end
$version
	Icarus Verilog
$end
$timescale
	100ps
$end
$scope module test_modulator $end
$var wire 1 ! pwm $end
$var reg 1 " clk $end
$var reg 1 # enable $end
$var reg 1 $ new_sample $end
$var reg 1 % rst $end
$var reg 8 & sample [7:0] $end
$scope module dut $end
$var wire 8 ' bits_per_sample [7:0] $end
$var wire 1 " clk $end
$var wire 8 ( clks_per_pwm_step [7:0] $end
$var wire 1 ) counter_rst $end
$var wire 1 # enable $end
$var wire 1 $ new_sample $end
$var wire 1 % rst $end
$var wire 8 * sample [7:0] $end
$var wire 1 + tc_pwm_symb $end
$var wire 1 , tc_pwm_step $end
$var reg 8 - counter_duty [7:0] $end
$var reg 1 ! pwm $end
$var reg 8 . sample_reg [7:0] $end
$scope module inst_counter_pwm_steps $end
$var wire 1 " clk $end
$var wire 1 / enable $end
$var wire 8 0 max_count [7:0] $end
$var wire 1 ) rst $end
$var wire 1 , tc $end
$var reg 8 1 count [7:0] $end
$var reg 1 2 tc2 $end
$upscope $end
$scope module inst_counter_pwm_symb $end
$var wire 1 " clk $end
$var wire 1 , enable $end
$var wire 8 3 max_count [7:0] $end
$var wire 1 ) rst $end
$var wire 1 + tc $end
$var reg 8 4 count [7:0] $end
$var reg 1 5 tc2 $end
$upscope $end
$upscope $end
$upscope $end
$enddefinitions $end
#0
$dumpvars
x5
bx 4
b11111111 3
x2
bx 1
b10 0
1/
bx .
bx -
x,
x+
bx *
1)
b10 (
b11111111 '
bx &
1%
0$
0#
0"
x!
$end
#100
b0 1
0,
02
b0 4
0+
05
b0 -
b0 .
1"
#200
0)
0%
0"
#300
0!
b1 1
1"
#400
1#
0"
#500
b10 1
1"
#600
1)
b10000000 &
b10000000 *
1$
0"
#700
b10000000 .
b0 1
1"
#800
0)
0$
0"
#900
b1 1
1"
#1000
0"
#1100
b10 1
1"
#1200
0"
#1300
1,
12
b0 1
1"
#1400
0"
#1500
1!
b1 -
b1 4
b1 1
0,
02
1"
#1600
0"
#1700
b10 1
1"
#1800
0"
#1900
1,
12
b0 1
1"
#2000
0"
#2100
b1 1
0,
02
b10 4
b10 -
1"
#2200
0"
#2300
b10 1
1"
#2400
0"
#2500
1,
12
b0 1
1"
#2600
0"
#2700
b11 -
b11 4
b1 1
0,
02
1"
#2800
0"
#2900
b10 1
1"
#3000
0"
#3100
1,
12
b0 1
1"
#3200
0"
#3300
b1 1
0,
02
b100 4
b100 -
1"
#3400
0"
#3500
b10 1
1"
#3600
0"
#3700
1,
12
b0 1
1"
#3800
0"
#3900
b101 -
b101 4
b1 1
0,
02
1"
#4000
0"
#4100
b10 1
1"
#4200
0"
#4300
1,
12
b0 1
1"
#4400
0"
#4500
b1 1
0,
02
b110 4
b110 -
1"
#4600
0"
#4700
b10 1
1"
#4800
0"
#4900
1,
12
b0 1
1"
#5000
0"
#5100
b111 -
b111 4
b1 1
0,
02
1"
#5200
0"
#5300
b10 1
1"
#5400
0"
#5500
1,
12
b0 1
1"
#5600
0"
#5700
b1 1
0,
02
b1000 4
b1000 -
1"
#5800
0"
#5900
b10 1
1"
#6000
0"
#6100
1,
12
b0 1
1"
#6200
0"
#6300
b1001 -
b1001 4
b1 1
0,
02
1"
#6400
0"
#6500
b10 1
1"
#6600
0"
#6700
1,
12
b0 1
1"
#6800
0"
#6900
b1 1
0,
02
b1010 4
b1010 -
1"
#7000
0"
#7100
b10 1
1"
#7200
0"
#7300
1,
12
b0 1
1"
#7400
0"
#7500
b1011 -
b1011 4
b1 1
0,
02
1"
#7600
0"
#7700
b10 1
1"
#7800
0"
#7900
1,
12
b0 1
1"
#8000
0"
#8100
b1 1
0,
02
b1100 4
b1100 -
1"
#8200
0"
#8300
b10 1
1"
#8400
0"
#8500
1,
12
b0 1
1"
#8600
0"
#8700
b1101 -
b1101 4
b1 1
0,
02
1"
#8800
0"
#8900
b10 1
1"
#9000
0"
#9100
1,
12
b0 1
1"
#9200
0"
#9300
b1 1
0,
02
b1110 4
b1110 -
1"
#9400
0"
#9500
b10 1
1"
#9600
0"
#9700
1,
12
b0 1
1"
#9800
0"
#9900
b1111 -
b1111 4
b1 1
0,
02
1"
#10000
0"
#10100
b10 1
1"
#10200
0"
#10300
1,
12
b0 1
1"
#10400
0"
#10500
b1 1
0,
02
b10000 4
b10000 -
1"
#10600
0"
#10700
b10 1
1"
#10800
0"
#10900
1,
12
b0 1
1"
#11000
0"
#11100
b10001 -
b10001 4
b1 1
0,
02
1"
#11200
0"
#11300
b10 1
1"
#11400
0"
#11500
1,
12
b0 1
1"
#11600
0"
#11700
b1 1
0,
02
b10010 4
b10010 -
1"
#11800
0"
#11900
b10 1
1"
#12000
0"
#12100
1,
12
b0 1
1"
#12200
0"
#12300
b10011 -
b10011 4
b1 1
0,
02
1"
#12400
0"
#12500
b10 1
1"
#12600
0"
#12700
1,
12
b0 1
1"
#12800
0"
#12900
b1 1
0,
02
b10100 4
b10100 -
1"
#13000
0"
#13100
b10 1
1"
#13200
0"
#13300
1,
12
b0 1
1"
#13400
0"
#13500
b10101 -
b10101 4
b1 1
0,
02
1"
#13600
0"
#13700
b10 1
1"
#13800
0"
#13900
1,
12
b0 1
1"
#14000
0"
#14100
b1 1
0,
02
b10110 4
b10110 -
1"
#14200
0"
#14300
b10 1
1"
#14400
0"
#14500
1,
12
b0 1
1"
#14600
0"
#14700
b10111 -
b10111 4
b1 1
0,
02
1"
#14800
0"
#14900
b10 1
1"
#15000
0"
#15100
1,
12
b0 1
1"
#15200
0"
#15300
b1 1
0,
02
b11000 4
b11000 -
1"
#15400
0"
#15500
b10 1
1"
#15600
0"
#15700
1,
12
b0 1
1"
#15800
0"
#15900
b11001 -
b11001 4
b1 1
0,
02
1"
#16000
0"
#16100
b10 1
1"
#16200
0"
#16300
1,
12
b0 1
1"
#16400
0"
#16500
b1 1
0,
02
b11010 4
b11010 -
1"
#16600
0"
#16700
b10 1
1"
#16800
0"
#16900
1,
12
b0 1
1"
#17000
0"
#17100
b11011 -
b11011 4
b1 1
0,
02
1"
#17200
0"
#17300
b10 1
1"
#17400
0"
#17500
1,
12
b0 1
1"
#17600
0"
#17700
b1 1
0,
02
b11100 4
b11100 -
1"
#17800
0"
#17900
b10 1
1"
#18000
0"
#18100
1,
12
b0 1
1"
#18200
0"
#18300
b11101 -
b11101 4
b1 1
0,
02
1"
#18400
0"
#18500
b10 1
1"
#18600
0"
#18700
1,
12
b0 1
1"
#18800
0"
#18900
b1 1
0,
02
b11110 4
b11110 -
1"
#19000
0"
#19100
b10 1
1"
#19200
0"
#19300
1,
12
b0 1
1"
#19400
0"
#19500
b11111 -
b11111 4
b1 1
0,
02
1"
#19600
0"
#19700
b10 1
1"
#19800
0"
#19900
1,
12
b0 1
1"
#20000
0"
#20100
b1 1
0,
02
b100000 4
b100000 -
1"
#20200
0"
#20300
b10 1
1"
#20400
0"
#20500
1,
12
b0 1
1"
#20600
0"
#20700
b100001 -
b100001 4
b1 1
0,
02
1"
#20800
0"
#20900
b10 1
1"
#21000
0"
#21100
1,
12
b0 1
1"
#21200
0"
#21300
b1 1
0,
02
b100010 4
b100010 -
1"
#21400
0"
#21500
b10 1
1"
#21600
0"
#21700
1,
12
b0 1
1"
#21800
0"
#21900
b100011 -
b100011 4
b1 1
0,
02
1"
#22000
0"
#22100
b10 1
1"
#22200
0"
#22300
1,
12
b0 1
1"
#22400
0"
#22500
b1 1
0,
02
b100100 4
b100100 -
1"
#22600
0"
#22700
b10 1
1"
#22800
0"
#22900
1,
12
b0 1
1"
#23000
0"
#23100
b100101 -
b100101 4
b1 1
0,
02
1"
#23200
0"
#23300
b10 1
1"
#23400
0"
#23500
1,
12
b0 1
1"
#23600
0"
#23700
b1 1
0,
02
b100110 4
b100110 -
1"
#23800
0"
#23900
b10 1
1"
#24000
0"
#24100
1,
12
b0 1
1"
#24200
0"
#24300
b100111 -
b100111 4
b1 1
0,
02
1"
#24400
0"
#24500
b10 1
1"
#24600
0"
#24700
1,
12
b0 1
1"
#24800
0"
#24900
b1 1
0,
02
b101000 4
b101000 -
1"
#25000
0"
#25100
b10 1
1"
#25200
0"
#25300
1,
12
b0 1
1"
#25400
0"
#25500
b101001 -
b101001 4
b1 1
0,
02
1"
#25600
0"
#25700
b10 1
1"
#25800
0"
#25900
1,
12
b0 1
1"
#26000
0"
#26100
b1 1
0,
02
b101010 4
b101010 -
1"
#26200
0"
#26300
b10 1
1"
#26400
0"
#26500
1,
12
b0 1
1"
#26600
0"
#26700
b101011 -
b101011 4
b1 1
0,
02
1"
#26800
0"
#26900
b10 1
1"
#27000
0"
#27100
1,
12
b0 1
1"
#27200
0"
#27300
b1 1
0,
02
b101100 4
b101100 -
1"
#27400
0"
#27500
b10 1
1"
#27600
0"
#27700
1,
12
b0 1
1"
#27800
0"
#27900
b101101 -
b101101 4
b1 1
0,
02
1"
#28000
0"
#28100
b10 1
1"
#28200
0"
#28300
1,
12
b0 1
1"
#28400
0"
#28500
b1 1
0,
02
b101110 4
b101110 -
1"
#28600
0"
#28700
b10 1
1"
#28800
0"
#28900
1,
12
b0 1
1"
#29000
0"
#29100
b101111 -
b101111 4
b1 1
0,
02
1"
#29200
0"
#29300
b10 1
1"
#29400
0"
#29500
1,
12
b0 1
1"
#29600
0"
#29700
b1 1
0,
02
b110000 4
b110000 -
1"
#29800
0"
#29900
b10 1
1"
#30000
0"
#30100
1,
12
b0 1
1"
#30200
0"
#30300
b110001 -
b110001 4
b1 1
0,
02
1"
#30400
0"
#30500
b10 1
1"
#30600
0"
#30700
1,
12
b0 1
1"
#30800
0"
#30900
b1 1
0,
02
b110010 4
b110010 -
1"
#31000
0"
#31100
b10 1
1"
#31200
0"
#31300
1,
12
b0 1
1"
#31400
0"
#31500
b110011 -
b110011 4
b1 1
0,
02
1"
#31600
0"
#31700
b10 1
1"
#31800
0"
#31900
1,
12
b0 1
1"
#32000
0"
#32100
b1 1
0,
02
b110100 4
b110100 -
1"
#32200
0"
#32300
b10 1
1"
#32400
0"
#32500
1,
12
b0 1
1"
#32600
0"
#32700
b110101 -
b110101 4
b1 1
0,
02
1"
#32800
0"
#32900
b10 1
1"
#33000
0"
#33100
1,
12
b0 1
1"
#33200
0"
#33300
b1 1
0,
02
b110110 4
b110110 -
1"
#33400
0"
#33500
b10 1
1"
#33600
0"
#33700
1,
12
b0 1
1"
#33800
0"
#33900
b110111 -
b110111 4
b1 1
0,
02
1"
#34000
0"
#34100
b10 1
1"
#34200
0"
#34300
1,
12
b0 1
1"
#34400
0"
#34500
b1 1
0,
02
b111000 4
b111000 -
1"
#34600
0"
#34700
b10 1
1"
#34800
0"
#34900
1,
12
b0 1
1"
#35000
0"
#35100
b111001 -
b111001 4
b1 1
0,
02
1"
#35200
0"
#35300
b10 1
1"
#35400
0"
#35500
1,
12
b0 1
1"
#35600
0"
#35700
b1 1
0,
02
b111010 4
b111010 -
1"
#35800
0"
#35900
b10 1
1"
#36000
0"
#36100
1,
12
b0 1
1"
#36200
0"
#36300
b111011 -
b111011 4
b1 1
0,
02
1"
#36400
0"
#36500
b10 1
1"
#36600
0"
#36700
1,
12
b0 1
1"
#36800
0"
#36900
b1 1
0,
02
b111100 4
b111100 -
1"
#37000
0"
#37100
b10 1
1"
#37200
0"
#37300
1,
12
b0 1
1"
#37400
0"
#37500
b111101 -
b111101 4
b1 1
0,
02
1"
#37600
0"
#37700
b10 1
1"
#37800
0"
#37900
1,
12
b0 1
1"
#38000
0"
#38100
b1 1
0,
02
b111110 4
b111110 -
1"
#38200
0"
#38300
b10 1
1"
#38400
0"
#38500
1,
12
b0 1
1"
#38600
0"
#38700
b111111 -
b111111 4
b1 1
0,
02
1"
#38800
0"
#38900
b10 1
1"
#39000
0"
#39100
1,
12
b0 1
1"
#39200
0"
#39300
b1 1
0,
02
b1000000 4
b1000000 -
1"
#39400
0"
#39500
b10 1
1"
#39600
0"
#39700
1,
12
b0 1
1"
#39800
0"
#39900
b1000001 -
b1000001 4
b1 1
0,
02
1"
#40000
0"
#40100
b10 1
1"
#40200
0"
#40300
1,
12
b0 1
1"
#40400
0"
#40500
b1 1
0,
02
b1000010 4
b1000010 -
1"
#40600
0"
#40700
b10 1
1"
#40800
0"
#40900
1,
12
b0 1
1"
#41000
0"
#41100
b1000011 -
b1000011 4
b1 1
0,
02
1"
#41200
0"
#41300
b10 1
1"
#41400
0"
#41500
1,
12
b0 1
1"
#41600
0"
#41700
b1 1
0,
02
b1000100 4
b1000100 -
1"
#41800
0"
#41900
b10 1
1"
#42000
0"
#42100
1,
12
b0 1
1"
#42200
0"
#42300
b1000101 -
b1000101 4
b1 1
0,
02
1"
#42400
0"
#42500
b10 1
1"
#42600
0"
#42700
1,
12
b0 1
1"
#42800
0"
#42900
b1 1
0,
02
b1000110 4
b1000110 -
1"
#43000
0"
#43100
b10 1
1"
#43200
0"
#43300
1,
12
b0 1
1"
#43400
0"
#43500
b1000111 -
b1000111 4
b1 1
0,
02
1"
#43600
0"
#43700
b10 1
1"
#43800
0"
#43900
1,
12
b0 1
1"
#44000
0"
#44100
b1 1
0,
02
b1001000 4
b1001000 -
1"
#44200
0"
#44300
b10 1
1"
#44400
0"
#44500
1,
12
b0 1
1"
#44600
0"
#44700
b1001001 -
b1001001 4
b1 1
0,
02
1"
#44800
0"
#44900
b10 1
1"
#45000
0"
#45100
1,
12
b0 1
1"
#45200
0"
#45300
b1 1
0,
02
b1001010 4
b1001010 -
1"
#45400
0"
#45500
b10 1
1"
#45600
0"
#45700
1,
12
b0 1
1"
#45800
0"
#45900
b1001011 -
b1001011 4
b1 1
0,
02
1"
#46000
0"
#46100
b10 1
1"
#46200
0"
#46300
1,
12
b0 1
1"
#46400
0"
#46500
b1 1
0,
02
b1001100 4
b1001100 -
1"
#46600
0"
#46700
b10 1
1"
#46800
0"
#46900
1,
12
b0 1
1"
#47000
0"
#47100
b1001101 -
b1001101 4
b1 1
0,
02
1"
#47200
0"
#47300
b10 1
1"
#47400
0"
#47500
1,
12
b0 1
1"
#47600
0"
#47700
b1 1
0,
02
b1001110 4
b1001110 -
1"
#47800
0"
#47900
b10 1
1"
#48000
0"
#48100
1,
12
b0 1
1"
#48200
0"
#48300
b1001111 -
b1001111 4
b1 1
0,
02
1"
#48400
0"
#48500
b10 1
1"
#48600
0"
#48700
1,
12
b0 1
1"
#48800
0"
#48900
b1 1
0,
02
b1010000 4
b1010000 -
1"
#49000
0"
#49100
b10 1
1"
#49200
0"
#49300
1,
12
b0 1
1"
#49400
0"
#49500
b1010001 -
b1010001 4
b1 1
0,
02
1"
#49600
0"
#49700
b10 1
1"
#49800
0"
#49900
1,
12
b0 1
1"
#50000
0"
#50100
b1 1
0,
02
b1010010 4
b1010010 -
1"
#50200
0"
#50300
b10 1
1"
#50400
0"
#50500
1,
12
b0 1
1"
#50600
0"
#50700
b1010011 -
b1010011 4
b1 1
0,
02
1"
#50800
0"
#50900
b10 1
1"
#51000
0"
#51100
1,
12
b0 1
1"
#51200
0"
#51300
b1 1
0,
02
b1010100 4
b1010100 -
1"
#51400
0"
#51500
b10 1
1"
#51600
0"
#51700
1,
12
b0 1
1"
#51800
0"
#51900
b1010101 -
b1010101 4
b1 1
0,
02
1"
#52000
0"
#52100
b10 1
1"
#52200
0"
#52300
1,
12
b0 1
1"
#52400
0"
#52500
b1 1
0,
02
b1010110 4
b1010110 -
1"
#52600
0"
#52700
b10 1
1"
#52800
0"
#52900
1,
12
b0 1
1"
#53000
0"
#53100
b1010111 -
b1010111 4
b1 1
0,
02
1"
#53200
0"
#53300
b10 1
1"
#53400
0"
#53500
1,
12
b0 1
1"
#53600
0"
#53700
b1 1
0,
02
b1011000 4
b1011000 -
1"
#53800
0"
#53900
b10 1
1"
#54000
0"
#54100
1,
12
b0 1
1"
#54200
0"
#54300
b1011001 -
b1011001 4
b1 1
0,
02
1"
#54400
0"
#54500
b10 1
1"
#54600
0"
#54700
1,
12
b0 1
1"
#54800
0"
#54900
b1 1
0,
02
b1011010 4
b1011010 -
1"
#55000
0"
#55100
b10 1
1"
#55200
0"
#55300
1,
12
b0 1
1"
#55400
0"
#55500
b1011011 -
b1011011 4
b1 1
0,
02
1"
#55600
0"
#55700
b10 1
1"
#55800
0"
#55900
1,
12
b0 1
1"
#56000
0"
#56100
b1 1
0,
02
b1011100 4
b1011100 -
1"
#56200
0"
#56300
b10 1
1"
#56400
0"
#56500
1,
12
b0 1
1"
#56600
0"
#56700
b1011101 -
b1011101 4
b1 1
0,
02
1"
#56800
0"
#56900
b10 1
1"
#57000
0"
#57100
1,
12
b0 1
1"
#57200
0"
#57300
b1 1
0,
02
b1011110 4
b1011110 -
1"
#57400
0"
#57500
b10 1
1"
#57600
0"
#57700
1,
12
b0 1
1"
#57800
0"
#57900
b1011111 -
b1011111 4
b1 1
0,
02
1"
#58000
0"
#58100
b10 1
1"
#58200
0"
#58300
1,
12
b0 1
1"
#58400
0"
#58500
b1 1
0,
02
b1100000 4
b1100000 -
1"
#58600
0"
#58700
b10 1
1"
#58800
0"
#58900
1,
12
b0 1
1"
#59000
0"
#59100
b1100001 -
b1100001 4
b1 1
0,
02
1"
#59200
0"
#59300
b10 1
1"
#59400
0"
#59500
1,
12
b0 1
1"
#59600
0"
#59700
b1 1
0,
02
b1100010 4
b1100010 -
1"
#59800
0"
#59900
b10 1
1"
#60000
0"
#60100
1,
12
b0 1
1"
#60200
0"
#60300
b1100011 -
b1100011 4
b1 1
0,
02
1"
#60400
0"
#60500
b10 1
1"
#60600
0"
#60700
1,
12
b0 1
1"
#60800
0"
#60900
b1 1
0,
02
b1100100 4
b1100100 -
1"
#61000
0"
#61100
b10 1
1"
#61200
0"
#61300
1,
12
b0 1
1"
#61400
0"
#61500
b1100101 -
b1100101 4
b1 1
0,
02
1"
#61600
0"
#61700
b10 1
1"
#61800
0"
#61900
1,
12
b0 1
1"
#62000
0"
#62100
b1 1
0,
02
b1100110 4
b1100110 -
1"
#62200
0"
#62300
b10 1
1"
#62400
0"
#62500
1,
12
b0 1
1"
#62600
0"
#62700
b1100111 -
b1100111 4
b1 1
0,
02
1"
#62800
0"
#62900
b10 1
1"
#63000
0"
#63100
1,
12
b0 1
1"
#63200
0"
#63300
b1 1
0,
02
b1101000 4
b1101000 -
1"
#63400
0"
#63500
b10 1
1"
#63600
0"
#63700
1,
12
b0 1
1"
#63800
0"
#63900
b1101001 -
b1101001 4
b1 1
0,
02
1"
#64000
0"
#64100
b10 1
1"
#64200
0"
#64300
1,
12
b0 1
1"
#64400
0"
#64500
b1 1
0,
02
b1101010 4
b1101010 -
1"
#64600
0"
#64700
b10 1
1"
#64800
0"
#64900
1,
12
b0 1
1"
#65000
0"
#65100
b1101011 -
b1101011 4
b1 1
0,
02
1"
#65200
0"
#65300
b10 1
1"
#65400
0"
#65500
1,
12
b0 1
1"
#65600
0"
#65700
b1 1
0,
02
b1101100 4
b1101100 -
1"
#65800
0"
#65900
b10 1
1"
#66000
0"
#66100
1,
12
b0 1
1"
#66200
0"
#66300
b1101101 -
b1101101 4
b1 1
0,
02
1"
#66400
0"
#66500
b10 1
1"
#66600
0"
#66700
1,
12
b0 1
1"
#66800
0"
#66900
b1 1
0,
02
b1101110 4
b1101110 -
1"
#67000
0"
#67100
b10 1
1"
#67200
0"
#67300
1,
12
b0 1
1"
#67400
0"
#67500
b1101111 -
b1101111 4
b1 1
0,
02
1"
#67600
0"
#67700
b10 1
1"
#67800
0"
#67900
1,
12
b0 1
1"
#68000
0"
#68100
b1 1
0,
02
b1110000 4
b1110000 -
1"
#68200
0"
#68300
b10 1
1"
#68400
0"
#68500
1,
12
b0 1
1"
#68600
0"
#68700
b1110001 -
b1110001 4
b1 1
0,
02
1"
#68800
0"
#68900
b10 1
1"
#69000
0"
#69100
1,
12
b0 1
1"
#69200
0"
#69300
b1 1
0,
02
b1110010 4
b1110010 -
1"
#69400
0"
#69500
b10 1
1"
#69600
0"
#69700
1,
12
b0 1
1"
#69800
0"
#69900
b1110011 -
b1110011 4
b1 1
0,
02
1"
#70000
0"
#70100
b10 1
1"
#70200
0"
#70300
1,
12
b0 1
1"
#70400
0"
#70500
b1 1
0,
02
b1110100 4
b1110100 -
1"
#70600
0"
#70700
b10 1
1"
#70800
0"
#70900
1,
12
b0 1
1"
#71000
0"
#71100
b1110101 -
b1110101 4
b1 1
0,
02
1"
#71200
0"
#71300
b10 1
1"
#71400
0"
#71500
1,
12
b0 1
1"
#71600
0"
#71700
b1 1
0,
02
b1110110 4
b1110110 -
1"
#71800
0"
#71900
b10 1
1"
#72000
0"
#72100
1,
12
b0 1
1"
#72200
0"
#72300
b1110111 -
b1110111 4
b1 1
0,
02
1"
#72400
0"
#72500
b10 1
1"
#72600
0"
#72700
1,
12
b0 1
1"
#72800
0"
#72900
b1 1
0,
02
b1111000 4
b1111000 -
1"
