inc/project_defines.v
/*
    This file have macros for address, intial values, number of registers and register width.
    Parameters are updated from this definition. DO NOT change it in other files or in instantiation (only do that for testing).

    REGS/REGISTERS/.. refers to normal registers.
    REQUEST_REGS/TRIGGER_REGS/... refers to registers that are erased after acknowledge the data reading.
    REGS_TOTAL/.. reefers to both.
*/

`ifndef __PROJECT_DEFINES_V
`define __PROJECT_DEFINES_V

/*******************************************************************************
                            HARDWARE DEFINITIONS
*******************************************************************************/
`define KILO                1000
`define MEGA                1000*`KILO




/*******************************************************************************
                            HARDWARE DEFINITIONS
*******************************************************************************/
`define CLK_FREQUENCY       128*`MEGA
`define CLOCK_PERIOD_NS     10




/*******************************************************************************
                            MODULATOR DEFINITIONS
*******************************************************************************/

// AM
`define AM_BIT_RESOLUTION       6
`define AM_PWM_STEPS            2**`AM_BIT_RESOLUTION
//`define AM_CARRIER_FREQ     CLK_FREQUENCY/AM_PWM_DIV
`define AM_CARRIER_FREQ         1*`MEGA
`define AM_CLKS_IN_PWM_STEPS    `CLK_FREQUENCY/(`AM_CARRIER_FREQ*`AM_PWM_STEPS)










/////////////////////////////
// USE REAL/FAKE ADCS
// real adc: ADC1175
// default fake adc version: loads rom.hex into a ROM (sinewave) + noise
// alternative fake adc version: counter
// To use fake adcs, add this defines when synthetising:
//  make syn DEF=FAKE_ADC                   # `define FAKE_ADC
//  make syn DEF="FAKE_ADC FAKE_ADC_ALT"    # `define FAKE_ADC_ALT
/////////////////////////////

`define CLK_FREQ        99000000
`define CLOCK_PERIOD_NS 10          // <-- correct this one

`define BAUDRATE        921600

`define __ADC_DF_WIDTH  32
`define __RAM_SIZE_CH   (4096*4)          // RAM for each channel in bits
`define __RAM_SIZE_CH_BYTES = (`__RAM_SIZE_CH / 8)
`define __MA_ACUM_WIDTH 12

/*******************************************************************************
                            HARDWARE DEFINITIONS
*******************************************************************************/
`define __BITS_ADC      8
`define __BITS_DAC      10

/*******************************************************************************
                            BASIC REGISTER DEFINITIONS
*******************************************************************************/

`define __FT245_DATA_WIDTH          8
`define __RX_WIDTH                  8       // Register and address width are a multiple of __RX_WIDTH
`define __TX_WIDTH                  8       //
`define __NUM_REGS                  15
`define __NUM_REQUEST_REGS          1
`define __NUM_REGS_TOTAL            ( __NUM_REGS + `__NUM_REQUEST_REGS )
`define __REG_DATA_WIDTH            16                                          // Register width
`define __REG_ADDR_WIDTH_MIN        ( $clog2( `__NUM_REGS_TOTAL ) )
//__ADDR_WIDTH_MIN rounded to next multiple of a byte
`define __REG_ADDR_WIDTH            ( $rtoi( $ceil( $itor(`__REG_ADDR_WIDTH_MIN) / `__RX_WIDTH ) ) * 8 )
`define __REGS_STARTING_ADDR        1                                           // First reg addr after request regs.

`define __ADC_CLK_DIV_WIDTH         32
`define __MOVING_AVERAGE_ACUM_WIDTH 12

`define __I2C_CLOCK_DIVIDER         1000
`define __I2C_FIFO_LENGTH           16

/*******************************************************************************
                                ADDRESSES
*******************************************************************************/

// Request regs addresses
`define __ADDR_REQUESTS                 0

// Conf regs addresses
`define __ADDR_SETTINGS_CHA             1
`define __ADDR_SETTINGS_CHB             2
`define __ADDR_DAC_I2C                  3
// `define __ADDR_DAC_CHA                  3
// `define __ADDR_DAC_CHB                  4
`define __ADDR_TRIGGER_SETTINGS         5
`define __ADDR_TRIGGER_VALUE            6
`define __ADDR_NUM_SAMPLES              7
`define __ADDR_PRETRIGGER               8
`define __ADDR_ADC_CLK_DIV_CHA_L        9
`define __ADDR_ADC_CLK_DIV_CHA_H        10
`define __ADDR_ADC_CLK_DIV_CHB_L        9
`define __ADDR_ADC_CLK_DIV_CHB_H        10
`define __ADDR_N_MOVING_AVERAGE_CHA     13
`define __ADDR_N_MOVING_AVERAGE_CHB     13

/*******************************************************************************
                                BIT FIELDS
*******************************************************************************/

// SETTINGS_CHA, SETTINGS_CHB
`define __CONF_CH_ATT                       7:5
`define __CONF_CH_GAIN                      4:2
`define __CONF_CH_DC_COUPLING               1:1
`define __CONF_CH_ON                        0:0

// trigger_conf
//`define __TRIGGER_CONF_MODE               3:3
`define __TRIGGER_CONF_SOURCE_SEL           2:1
`define __TRIGGER_CONF_EDGE                 0

// Requests handler
`define __RQST_START_IDX        0
`define __RQST_STOP_IDX         1
`define __RQST_CHA_IDX          2
`define __RQST_CHB_IDX          3
`define __RQST_TRIG_IDX         4
`define __RQST_RST_IDX          5

/*******************************************************************************
                        INITIAL VALUES OF REGESTERS
*******************************************************************************/

`define __DEFAULT_REQUESTS               16'd0
`define __DEFAULT_SETTINGS_CHA           16'b0000000000000011
`define __DEFAULT_SETTINGS_CHB           16'b0000000000000011
// `define __DEFAULT_DAC_CHA                (1 << (`__BITS_DAC-1)) // 16'b1000000000000000
// `define __DEFAULT_DAC_CHB                (1 << (`__BITS_DAC-1)) // 16'b1000000000000000
`define __DEFAULT_DAC_I2C                16'd0
`define __DEFAULT_TRIGGER_SETTINGS       16'd0
`define __DEFAULT_TRIGGER_VALUE          (1 << (`__BITS_ADC-1)) // 16'b10000000
`define __DEFAULT_NUM_SAMPLES            16'd128
`define __DEFAULT_PRETRIGGER             16'd28
`define __DEFAULT_ADC_CLK_DIV_CHA        16'd4
`define __DEFAULT_ADC_CLK_DIV_CHB        16'd4
`define __DEFAULT_N_MOVING_AVERAGE_CHA   16'd0
`define __DEFAULT_N_MOVING_AVERAGE_CHB   16'd0

`endif

modules/counter/counter.v
/* module */

module counter #(
    parameter MODULE = 50000000
)(
    input   clk,
    input   rst,
    input   enable,
    output  tc
);
    localparam WIDTH = $clog2(MODULE);

    /* Counter register */
    reg [WIDTH-1:0] count;
    reg tc2;
    assign tc=tc2;

    /* always */
    always @ (posedge clk) begin
        tc2 <= 1'b0;

        if (rst == 1'b1)
            count <=0;
        else if ( enable == 1'b1 ) begin
            count <= count + 1;
            if ( count == MODULE ) begin
                count <= 0;
                tc2 <= 1'b1;
            end
        end
    end

endmodule

modules/modulator/modulator.v
`include "../../inc/project_defines.v"

module modulator #(
    parameter FOO = 10,
    parameter AM_CLKS_IN_PWM_STEPS = `AM_PWM_STEPS,
    parameter AM_PWM_STEPS = `AM_PWM_STEPS
)(
    input clk,
    input rst,
    output pwm
);
    localparam WIDTH = $clog2(FOO);

    /* registers */
    reg [WIDTH-1:0] count;
    wire tc_pwm_step, tc_pwm_symb;
    reg [AM_PWM_STEPS-1:0] shift_register;


    /******** testing signals ********/
    reg [100-1:0] sine_10k;
    reg [6:0] counter_sine_10k;
    /******** testing signals ********/


    // counter to generate ticks at pwm-steps frequency
    counter #(
        .MODULE  (AM_CLKS_IN_PWM_STEPS)
    ) inst_counter_pwm_steps (
        .clk    (clk),
        .rst    (rst),
        .enable (1'b1),
        .tc     (tc_pwm_step)
    );

    // counter to generate ticks at pwm-symbols frequency
    counter #(
        .MODULE  (AM_PWM_STEPS)
    ) inst_counter_pwm_symb (
        .clk    (clk),
        .rst    (rst),
        .enable (tc_pwm_step),
        .tc     (tc_pwm_symb)
    );

    // shift register to serialize each pwm-symbol
    always @ (posedge clk) begin
        if(rst == 1'b1)
            shift_register <= `AM_PWM_STEPS'd0;
        else if (tc_pwm_symb == 1'b1) begin
            counter_sine_10k <= counter_sine_10k + 1;
            case(counter_sine_10k)
                // 0 - 10
                 7'd1:   shift_register <= 64'd1111111111111111111111111111111100000000000000000000000000000000;
                 7'd2:   shift_register <= 64'd1111111111111111111111111111111110000000000000000000000000000000;
                 7'd3:   shift_register <= 64'd1111111111111111111111111111111111100000000000000000000000000000;
                 7'd0:   shift_register <= 64'd1111111111111111111111111111111111111000000000000000000000000000;
                 7'd4:   shift_register <= 64'd1111111111111111111111111111111111111110000000000000000000000000;
                 7'd5:   shift_register <= 64'd1111111111111111111111111111111111111111100000000000000000000000;
                 7'd6:   shift_register <= 64'd1111111111111111111111111111111111111111111000000000000000000000;
                 7'd7:   shift_register <= 64'd1111111111111111111111111111111111111111111110000000000000000000;
                 7'd8:   shift_register <= 64'd1111111111111111111111111111111111111111111111100000000000000000;
                 7'd9:   shift_register <= 64'd1111111111111111111111111111111111111111111111110000000000000000;
                7'd10:   shift_register <= 64'd1111111111111111111111111111111111111111111111111100000000000000;
                7'd11:   shift_register <= 64'd1111111111111111111111111111111111111111111111111111000000000000;
                7'd12:   shift_register <= 64'd1111111111111111111111111111111111111111111111111111100000000000;
                7'd13:   shift_register <= 64'd1111111111111111111111111111111111111111111111111111110000000000;
                7'd14:   shift_register <= 64'd1111111111111111111111111111111111111111111111111111111100000000;
                7'd15:   shift_register <= 64'd1111111111111111111111111111111111111111111111111111111110000000;
                7'd16:   shift_register <= 64'd1111111111111111111111111111111111111111111111111111111111000000;
                7'd17:   shift_register <= 64'd1111111111111111111111111111111111111111111111111111111111100000;
                7'd18:   shift_register <= 64'd1111111111111111111111111111111111111111111111111111111111110000;
                7'd19:   shift_register <= 64'd1111111111111111111111111111111111111111111111111111111111111000;
                7'd20:   shift_register <= 64'd1111111111111111111111111111111111111111111111111111111111111000;
                7'd21:   shift_register <= 64'd1111111111111111111111111111111111111111111111111111111111111100;
                7'd22:   shift_register <= 64'd1111111111111111111111111111111111111111111111111111111111111100;
                7'd23:   shift_register <= 64'd1111111111111111111111111111111111111111111111111111111111111110;
                7'd24:   shift_register <= 64'd1111111111111111111111111111111111111111111111111111111111111110;
                7'd25:   shift_register <= 64'd1111111111111111111111111111111111111111111111111111111111111110;
                7'd26:   shift_register <= 64'd1111111111111111111111111111111111111111111111111111111111111110;
                7'd27:   shift_register <= 64'd1111111111111111111111111111111111111111111111111111111111111110;
                7'd28:   shift_register <= 64'd1111111111111111111111111111111111111111111111111111111111111100;
                7'd29:   shift_register <= 64'd1111111111111111111111111111111111111111111111111111111111111100;
                7'd30:   shift_register <= 64'd1111111111111111111111111111111111111111111111111111111111111000;
                7'd31:   shift_register <= 64'd1111111111111111111111111111111111111111111111111111111111111000;
                7'd32:   shift_register <= 64'd1111111111111111111111111111111111111111111111111111111111110000;
                7'd33:   shift_register <= 64'd1111111111111111111111111111111111111111111111111111111111100000;
                7'd34:   shift_register <= 64'd1111111111111111111111111111111111111111111111111111111111000000;
                7'd35:   shift_register <= 64'd1111111111111111111111111111111111111111111111111111111110000000;
                7'd36:   shift_register <= 64'd1111111111111111111111111111111111111111111111111111111100000000;
                7'd37:   shift_register <= 64'd1111111111111111111111111111111111111111111111111111110000000000;
                7'd38:   shift_register <= 64'd1111111111111111111111111111111111111111111111111111100000000000;
                7'd39:   shift_register <= 64'd1111111111111111111111111111111111111111111111111111000000000000;
                7'd40:   shift_register <= 64'd1111111111111111111111111111111111111111111111111100000000000000;
                7'd41:   shift_register <= 64'd1111111111111111111111111111111111111111111111110000000000000000;
                7'd42:   shift_register <= 64'd1111111111111111111111111111111111111111111111100000000000000000;
                7'd43:   shift_register <= 64'd1111111111111111111111111111111111111111111110000000000000000000;
                7'd44:   shift_register <= 64'd1111111111111111111111111111111111111111111000000000000000000000;
                7'd45:   shift_register <= 64'd1111111111111111111111111111111111111111100000000000000000000000;
                7'd46:   shift_register <= 64'd1111111111111111111111111111111111111110000000000000000000000000;
                7'd47:   shift_register <= 64'd1111111111111111111111111111111111111000000000000000000000000000;
                7'd48:   shift_register <= 64'd1111111111111111111111111111111111100000000000000000000000000000;
                7'd49:   shift_register <= 64'd1111111111111111111111111111111110000000000000000000000000000000;
                7'd50:   shift_register <= 64'd1111111111111111111111111111111000000000000000000000000000000000;
                7'd51:   shift_register <= 64'd1111111111111111111111111111110000000000000000000000000000000000;
                7'd52:   shift_register <= 64'd1111111111111111111111111111000000000000000000000000000000000000;
                7'd53:   shift_register <= 64'd1111111111111111111111111100000000000000000000000000000000000000;
                7'd54:   shift_register <= 64'd1111111111111111111111110000000000000000000000000000000000000000;
                7'd55:   shift_register <= 64'd1111111111111111111111000000000000000000000000000000000000000000;
                7'd56:   shift_register <= 64'd1111111111111111111100000000000000000000000000000000000000000000;
                7'd57:   shift_register <= 64'd1111111111111111110000000000000000000000000000000000000000000000;
                7'd58:   shift_register <= 64'd1111111111111111000000000000000000000000000000000000000000000000;
                7'd59:   shift_register <= 64'd1111111111111110000000000000000000000000000000000000000000000000;
                7'd60:   shift_register <= 64'd1111111111111000000000000000000000000000000000000000000000000000;
                7'd61:   shift_register <= 64'd1111111111100000000000000000000000000000000000000000000000000000;
                7'd62:   shift_register <= 64'd1111111111000000000000000000000000000000000000000000000000000000;
                7'd63:   shift_register <= 64'd1111111110000000000000000000000000000000000000000000000000000000;
                7'd64:   shift_register <= 64'd1111111000000000000000000000000000000000000000000000000000000000;
                7'd65:   shift_register <= 64'd1111110000000000000000000000000000000000000000000000000000000000;
                7'd66:   shift_register <= 64'd1111100000000000000000000000000000000000000000000000000000000000;
                7'd67:   shift_register <= 64'd1111000000000000000000000000000000000000000000000000000000000000;
                7'd68:   shift_register <= 64'd1110000000000000000000000000000000000000000000000000000000000000;
                7'd69:   shift_register <= 64'd1100000000000000000000000000000000000000000000000000000000000000;
                7'd70:   shift_register <= 64'd1100000000000000000000000000000000000000000000000000000000000000;
                7'd71:   shift_register <= 64'd1000000000000000000000000000000000000000000000000000000000000000;
                7'd72:   shift_register <= 64'd1000000000000000000000000000000000000000000000000000000000000000;
                7'd73:   shift_register <= 64'd0000000000000000000000000000000000000000000000000000000000000000;
                7'd74:   shift_register <= 64'd0000000000000000000000000000000000000000000000000000000000000000;
                7'd75:   shift_register <= 64'd0000000000000000000000000000000000000000000000000000000000000000;
                7'd76:   shift_register <= 64'd0000000000000000000000000000000000000000000000000000000000000000;
                7'd77:   shift_register <= 64'd0000000000000000000000000000000000000000000000000000000000000000;
                7'd78:   shift_register <= 64'd1000000000000000000000000000000000000000000000000000000000000000;
                7'd79:   shift_register <= 64'd1000000000000000000000000000000000000000000000000000000000000000;
                7'd80:   shift_register <= 64'd1100000000000000000000000000000000000000000000000000000000000000;
                7'd81:   shift_register <= 64'd1100000000000000000000000000000000000000000000000000000000000000;
                7'd82:   shift_register <= 64'd1110000000000000000000000000000000000000000000000000000000000000;
                7'd83:   shift_register <= 64'd1111000000000000000000000000000000000000000000000000000000000000;
                7'd84:   shift_register <= 64'd1111100000000000000000000000000000000000000000000000000000000000;
                7'd85:   shift_register <= 64'd1111110000000000000000000000000000000000000000000000000000000000;
                7'd86:   shift_register <= 64'd1111111000000000000000000000000000000000000000000000000000000000;
                7'd87:   shift_register <= 64'd1111111110000000000000000000000000000000000000000000000000000000;
                7'd88:   shift_register <= 64'd1111111111000000000000000000000000000000000000000000000000000000;
                7'd89:   shift_register <= 64'd1111111111100000000000000000000000000000000000000000000000000000;
                7'd90:   shift_register <= 64'd1111111111111000000000000000000000000000000000000000000000000000;
                7'd91:   shift_register <= 64'd1111111111111110000000000000000000000000000000000000000000000000;
                7'd92:   shift_register <= 64'd1111111111111111000000000000000000000000000000000000000000000000;
                7'd93:   shift_register <= 64'd1111111111111111110000000000000000000000000000000000000000000000;
                7'd94:   shift_register <= 64'd1111111111111111111100000000000000000000000000000000000000000000;
                7'd95:   shift_register <= 64'd1111111111111111111111000000000000000000000000000000000000000000;
                7'd96:   shift_register <= 64'd1111111111111111111111110000000000000000000000000000000000000000;
                7'd97:   shift_register <= 64'd1111111111111111111111111100000000000000000000000000000000000000;
                7'd98:   shift_register <= 64'd1111111111111111111111111111000000000000000000000000000000000000;
                7'd99:   shift_register <= 64'd1111111111111111111111111111110000000000000000000000000000000000;

                default:
                    shift_register <= 64'd0;                    
            endcase
        end else if (tc_pwm_step == 1'b1)
            shift_register <= {shift_register[AM_PWM_STEPS-2:0],shift_register[AM_PWM_STEPS-1]};
    end

    // output assignment
    assign pwm = shift_register[AM_PWM_STEPS-1];

endmodule

modules/modulator/modulator_tb.v
`include "../../inc/project_defines.v"

module test_modulator;

  reg rst = 1;

  
  /* Make a regular pulsing clock. */
  reg clk = 0;

  always #1 clk = !clk;


  modulator  #(.FOO(10),.AM_CLKS_IN_PWM_STEPS(`AM_PWM_STEPS),.AM_PWM_STEPS(`AM_PWM_STEPS))
  				 dut (clk,rst,pwm);

        initial begin
            $dumpfile ("waveform.vcd");
            $dumpvars (0,test_modulator);
            rst<=1;
            #5
            rst<=0;
            
            #2005;
            $finish;

        end
endmodule

modules/modulator/waveform.vcd
$date
	Thu Sep  5 22:42:11 2019
$end
$version
	Icarus Verilog
$end
$timescale
	1s
$end
$scope module test_modulator $end
$var wire 1 ! pwm $end
$var reg 1 " clk $end
$var reg 1 # rst $end
$scope module dut $end
$var wire 1 " clk $end
$var wire 1 # rst $end
$var wire 1 $ tc_pwm_symb $end
$var wire 1 % tc_pwm_step $end
$var wire 1 ! pwm $end
$var reg 7 & counter_sine_10k [6:0] $end
$var reg 64 ' shift_register [63:0] $end
$scope module inst_counter_pwm_steps $end
$var wire 1 " clk $end
$var wire 1 ( enable $end
$var wire 1 # rst $end
$var wire 1 % tc $end
$var reg 6 ) count [5:0] $end
$var reg 1 * tc2 $end
$upscope $end
$scope module inst_counter_pwm_symb $end
$var wire 1 " clk $end
$var wire 1 % enable $end
$var wire 1 # rst $end
$var wire 1 $ tc $end
$var reg 6 + count [5:0] $end
$var reg 1 , tc2 $end
$upscope $end
$upscope $end
$upscope $end
$enddefinitions $end
#0
$dumpvars
x,
bx +
x*
bx )
1(
bx '
bx &
x%
x$
1#
0"
x!
$end
#1
0!
b0 )
0%
0*
b0 +
0$
0,
b1 '
1"
#2
0"
#3
1"
#4
0"
#5
0#
1"
#6
0"
#7
b1 )
1"
#8
0"
#9
b10 )
1"
#10
0"
#11
b11 )
1"
#12
0"
#13
b100 )
1"
#14
0"
#15
b101 )
1"
#16
0"
#17
b110 )
1"
#18
0"
#19
b111 )
1"
#20
0"
#21
b1000 )
1"
#22
0"
#23
b1001 )
1"
#24
0"
#25
b1010 )
1"
#26
0"
#27
b1011 )
1"
#28
0"
#29
b1100 )
1"
#30
0"
#31
b1101 )
1"
#32
0"
#33
b1110 )
1"
#34
0"
#35
b1111 )
1"
#36
0"
#37
b10000 )
1"
#38
0"
#39
b10001 )
1"
#40
0"
#41
b10010 )
1"
#42
0"
#43
b10011 )
1"
#44
0"
#45
b10100 )
1"
#46
0"
#47
b10101 )
1"
#48
0"
#49
b10110 )
1"
#50
0"
#51
b10111 )
1"
#52
0"
#53
b11000 )
1"
#54
0"
#55
b11001 )
1"
#56
0"
#57
b11010 )
1"
#58
0"
#59
b11011 )
1"
#60
0"
#61
b11100 )
1"
#62
0"
#63
b11101 )
1"
#64
0"
#65
b11110 )
1"
#66
0"
#67
b11111 )
1"
#68
0"
#69
b100000 )
1"
#70
0"
#71
b100001 )
1"
#72
0"
#73
b100010 )
1"
#74
0"
#75
b100011 )
1"
#76
0"
#77
b100100 )
1"
#78
0"
#79
b100101 )
1"
#80
0"
#81
b100110 )
1"
#82
0"
#83
b100111 )
1"
#84
0"
#85
b101000 )
1"
#86
0"
#87
b101001 )
1"
#88
0"
#89
b101010 )
1"
#90
0"
#91
b101011 )
1"
#92
0"
#93
b101100 )
1"
#94
0"
#95
b101101 )
1"
#96
0"
#97
b101110 )
1"
#98
0"
#99
b101111 )
1"
#100
0"
#101
b110000 )
1"
#102
0"
#103
b110001 )
1"
#104
0"
#105
b110010 )
1"
#106
0"
#107
b110011 )
1"
#108
0"
#109
b110100 )
1"
#110
0"
#111
b110101 )
1"
#112
0"
#113
b110110 )
1"
#114
0"
#115
b110111 )
1"
#116
0"
#117
b111000 )
1"
#118
0"
#119
b111001 )
1"
#120
0"
#121
b111010 )
1"
#122
0"
#123
b111011 )
1"
#124
0"
#125
b111100 )
1"
#126
0"
#127
b111101 )
1"
#128
0"
#129
b111110 )
1"
#130
0"
#131
b111111 )
1"
#132
0"
#133
b0 )
1"
#134
0"
#135
b1 )
1"
#136
0"
#137
b10 )
1"
#138
0"
#139
b11 )
1"
#140
0"
#141
b100 )
1"
#142
0"
#143
b101 )
1"
#144
0"
#145
b110 )
1"
#146
0"
#147
b111 )
1"
#148
0"
#149
b1000 )
1"
#150
0"
#151
b1001 )
1"
#152
0"
#153
b1010 )
1"
#154
0"
#155
b1011 )
1"
#156
0"
#157
b1100 )
1"
#158
0"
#159
b1101 )
1"
#160
0"
#161
b1110 )
1"
#162
0"
#163
b1111 )
1"
#164
0"
#165
b10000 )
1"
#166
0"
#167
b10001 )
1"
#168
0"
#169
b10010 )
1"
#170
0"
#171
b10011 )
1"
#172
0"
#173
b10100 )
1"
#174
0"
#175
b10101 )
1"
#176
0"
#177
b10110 )
1"
#178
0"
#179
b10111 )
1"
#180
0"
#181
b11000 )
1"
#182
0"
#183
b11001 )
1"
#184
0"
#185
b11010 )
1"
#186
0"
#187
b11011 )
1"
#188
0"
#189
b11100 )
1"
#190
0"
#191
b11101 )
1"
#192
0"
#193
b11110 )
1"
#194
0"
#195
b11111 )
1"
#196
0"
#197
b100000 )
1"
#198
0"
#199
b100001 )
1"
#200
0"
#201
b100010 )
1"
#202
0"
#203
b100011 )
1"
#204
0"
#205
b100100 )
1"
#206
0"
#207
b100101 )
1"
#208
0"
#209
b100110 )
1"
#210
0"
#211
b100111 )
1"
#212
0"
#213
b101000 )
1"
#214
0"
#215
b101001 )
1"
#216
0"
#217
b101010 )
1"
#218
0"
#219
b101011 )
1"
#220
0"
#221
b101100 )
1"
#222
0"
#223
b101101 )
1"
#224
0"
#225
b101110 )
1"
#226
0"
#227
b101111 )
1"
#228
0"
#229
b110000 )
1"
#230
0"
#231
b110001 )
1"
#232
0"
#233
b110010 )
1"
#234
0"
#235
b110011 )
1"
#236
0"
#237
b110100 )
1"
#238
0"
#239
b110101 )
1"
#240
0"
#241
b110110 )
1"
#242
0"
#243
b110111 )
1"
#244
0"
#245
b111000 )
1"
#246
0"
#247
b111001 )
1"
#248
0"
#249
b111010 )
1"
#250
0"
#251
b111011 )
1"
#252
0"
#253
b111100 )
1"
#254
0"
#255
b111101 )
1"
#256
0"
#257
b111110 )
1"
#258
0"
#259
b111111 )
1"
#260
0"
#261
b0 )
1"
#262
0"
#263
b1 )
1"
#264
0"
#265
b10 )
1"
#266
0"
#267
b11 )
1"
#268
0"
#269
b100 )
1"
#270
0"
#271
b101 )
1"
#272
0"
#273
b110 )
1"
#274
0"
#275
b111 )
1"
#276
0"
#277
b1000 )
1"
#278
0"
#279
b1001 )
1"
#280
0"
#281
b1010 )
1"
#282
0"
#283
b1011 )
1"
#284
0"
#285
b1100 )
1"
#286
0"
#287
b1101 )
1"
#288
0"
#289
b1110 )
1"
#290
0"
#291
b1111 )
1"
#292
0"
#293
b10000 )
1"
#294
0"
#295
b10001 )
1"
#296
0"
#297
b10010 )
1"
#298
0"
#299
b10011 )
1"
#300
0"
#301
b10100 )
1"
#302
0"
#303
b10101 )
1"
#304
0"
#305
b10110 )
1"
#306
0"
#307
b10111 )
1"
#308
0"
#309
b11000 )
1"
#310
0"
#311
b11001 )
1"
#312
0"
#313
b11010 )
1"
#314
0"
#315
b11011 )
1"
#316
0"
#317
b11100 )
1"
#318
0"
#319
b11101 )
1"
#320
0"
#321
b11110 )
1"
#322
0"
#323
b11111 )
1"
#324
0"
#325
b100000 )
1"
#326
0"
#327
b100001 )
1"
#328
0"
#329
b100010 )
1"
#330
0"
#331
b100011 )
1"
#332
0"
#333
b100100 )
1"
#334
0"
#335
b100101 )
1"
#336
0"
#337
b100110 )
1"
#338
0"
#339
b100111 )
1"
#340
0"
#341
b101000 )
1"
#342
0"
#343
b101001 )
1"
#344
0"
#345
b101010 )
1"
#346
0"
#347
b101011 )
1"
#348
0"
#349
b101100 )
1"
#350
0"
#351
b101101 )
1"
#352
0"
#353
b101110 )
1"
#354
0"
#355
b101111 )
1"
#356
0"
#357
b110000 )
1"
#358
0"
#359
b110001 )
1"
#360
0"
#361
b110010 )
1"
#362
0"
#363
b110011 )
1"
#364
0"
#365
b110100 )
1"
#366
0"
#367
b110101 )
1"
#368
0"
#369
b110110 )
1"
#370
0"
#371
b110111 )
1"
#372
0"
#373
b111000 )
1"
#374
0"
#375
b111001 )
1"
#376
0"
#377
b111010 )
1"
#378
0"
#379
b111011 )
1"
#380
0"
#381
b111100 )
1"
#382
0"
#383
b111101 )
1"
#384
0"
#385
b111110 )
1"
#386
0"
#387
b111111 )
1"
#388
0"
#389
b0 )
1"
#390
0"
#391
b1 )
1"
#392
0"
#393
b10 )
1"
#394
0"
#395
b11 )
1"
#396
0"
#397
b100 )
1"
#398
0"
#399
b101 )
1"
#400
0"
#401
b110 )
1"
#402
0"
#403
b111 )
1"
#404
0"
#405
b1000 )
1"
#406
0"
#407
b1001 )
1"
#408
0"
#409
b1010 )
1"
#410
0"
#411
b1011 )
1"
#412
0"
#413
b1100 )
1"
#414
0"
#415
b1101 )
1"
#416
0"
#417
b1110 )
1"
#418
0"
#419
b1111 )
1"
#420
0"
#421
b10000 )
1"
#422
0"
#423
b10001 )
1"
#424
0"
#425
b10010 )
1"
#426
0"
#427
b10011 )
1"
#428
0"
#429
b10100 )
1"
#430
0"
#431
b10101 )
1"
#432
0"
#433
b10110 )
1"
#434
0"
#435
b10111 )
1"
#436
0"
#437
b11000 )
1"
#438
0"
#439
b11001 )
1"
#440
0"
#441
b11010 )
1"
#442
0"
#443
b11011 )
1"
#444
0"
#445
b11100 )
1"
#446
0"
#447
b11101 )
1"
#448
0"
#449
b11110 )
1"
#450
0"
#451
b11111 )
1"
#452
0"
#453
b100000 )
1"
#454
0"
#455
b100001 )
1"
#456
0"
#457
b100010 )
1"
#458
0"
#459
b100011 )
1"
#460
0"
#461
b100100 )
1"
#462
0"
#463
b100101 )
1"
#464
0"
#465
b100110 )
1"
#466
0"
#467
b100111 )
1"
#468
0"
#469
b101000 )
1"
#470
0"
#471
b101001 )
1"
#472
0"
#473
b101010 )
1"
#474
0"
#475
b101011 )
1"
#476
0"
#477
b101100 )
1"
#478
0"
#479
b101101 )
1"
#480
0"
#481
b101110 )
1"
#482
0"
#483
b101111 )
1"
#484
0"
#485
b110000 )
1"
#486
0"
#487
b110001 )
1"
#488
0"
#489
b110010 )
1"
#490
0"
#491
b110011 )
1"
#492
0"
#493
b110100 )
1"
#494
0"
#495
b110101 )
1"
#496
0"
#497
b110110 )
1"
#498
0"
#499
b110111 )
1"
#500
0"
#501
b111000 )
1"
#502
0"
#503
b111001 )
1"
#504
0"
#505
b111010 )
1"
#506
0"
#507
b111011 )
1"
#508
0"
#509
b111100 )
1"
#510
0"
#511
b111101 )
1"
#512
0"
#513
b111110 )
1"
#514
0"
#515
b111111 )
1"
#516
0"
#517
b0 )
1"
#518
0"
#519
b1 )
1"
#520
0"
#521
b10 )
1"
#522
0"
#523
b11 )
1"
#524
0"
#525
b100 )
1"
#526
0"
#527
b101 )
1"
#528
0"
#529
b110 )
1"
#530
0"
#531
b111 )
1"
#532
0"
#533
b1000 )
1"
#534
0"
#535
b1001 )
1"
#536
0"
#537
b1010 )
1"
#538
0"
#539
b1011 )
1"
#540
0"
#541
b1100 )
1"
#542
0"
#543
b1101 )
1"
#544
0"
#545
b1110 )
1"
#546
0"
#547
b1111 )
1"
#548
0"
#549
b10000 )
1"
#550
0"
#551
b10001 )
1"
#552
0"
#553
b10010 )
1"
#554
0"
#555
b10011 )
1"
#556
0"
#557
b10100 )
1"
#558
0"
#559
b10101 )
1"
#560
0"
#561
b10110 )
1"
#562
0"
#563
b10111 )
1"
#564
0"
#565
b11000 )
1"
#566
0"
#567
b11001 )
1"
#568
0"
#569
b11010 )
1"
#570
0"
#571
b11011 )
1"
#572
0"
#573
b11100 )
1"
#574
0"
#575
b11101 )
1"
#576
0"
#577
b11110 )
1"
#578
0"
#579
b11111 )
1"
#580
0"
#581
b100000 )
1"
#582
0"
#583
b100001 )
1"
#584
0"
#585
b100010 )
1"
#586
0"
#587
b100011 )
1"
#588
0"
#589
b100100 )
1"
#590
0"
#591
b100101 )
1"
#592
0"
#593
b100110 )
1"
#594
0"
#595
b100111 )
1"
#596
0"
#597
b101000 )
1"
#598
0"
#599
b101001 )
1"
#600
0"
#601
b101010 )
1"
#602
0"
#603
b101011 )
1"
#604
0"
#605
b101100 )
1"
#606
0"
#607
b101101 )
1"
#608
0"
#609
b101110 )
1"
#610
0"
#611
b101111 )
1"
#612
0"
#613
b110000 )
1"
#614
0"
#615
b110001 )
1"
#616
0"
#617
b110010 )
1"
#618
0"
#619
b110011 )
1"
#620
0"
#621
b110100 )
1"
#622
0"
#623
b110101 )
1"
#624
0"
#625
b110110 )
1"
#626
0"
#627
b110111 )
1"
#628
0"
#629
b111000 )
1"
#630
0"
#631
b111001 )
1"
#632
0"
#633
b111010 )
1"
#634
0"
#635
b111011 )
1"
#636
0"
#637
b111100 )
1"
#638
0"
#639
b111101 )
1"
#640
0"
#641
b111110 )
1"
#642
0"
#643
b111111 )
1"
#644
0"
#645
b0 )
1"
#646
0"
#647
b1 )
1"
#648
0"
#649
b10 )
1"
#650
0"
#651
b11 )
1"
#652
0"
#653
b100 )
1"
#654
0"
#655
b101 )
1"
#656
0"
#657
b110 )
1"
#658
0"
#659
b111 )
1"
#660
0"
#661
b1000 )
1"
#662
0"
#663
b1001 )
1"
#664
0"
#665
b1010 )
1"
#666
0"
#667
b1011 )
1"
#668
0"
#669
b1100 )
1"
#670
0"
#671
b1101 )
1"
#672
0"
#673
b1110 )
1"
#674
0"
#675
b1111 )
1"
#676
0"
#677
b10000 )
1"
#678
0"
#679
b10001 )
1"
#680
0"
#681
b10010 )
1"
#682
0"
#683
b10011 )
1"
#684
0"
#685
b10100 )
1"
#686
0"
#687
b10101 )
1"
#688
0"
#689
b10110 )
1"
#690
0"
#691
b10111 )
1"
#692
0"
#693
b11000 )
1"
#694
0"
#695
b11001 )
1"
#696
0"
#697
b11010 )
1"
#698
0"
#699
b11011 )
1"
#700
0"
